[
    {
        "id": 4,
        "img": "https://raw.githubusercontent.com/Z9625/cards-data/refs/heads/main/Kukeldash1.jpg",
        "h1": "Ko’kaldosh Maqbarasi",
        "p": "Ko’kaldosh Maqbarasi, Toshkent",
        "about": "Ko’kaldosh Madrasasi bu Toshkent shahrining eng ko’p tanilgan tarixiy binolaridan biridir. Ushbu Madrasa Shayboniylar sulolasi vakili Darveshxon tomonidan 1551-75 yillar, ya’ni 24 yil davomida qurilib ishga tushirilgan. Shu sababli madrasaga ‘Darveshxon’ madrasasi ham deb ataladi. \n\n Ko’kaldosh Madrasasi Toshkent shahrining eng birinchi masjidlaridan biri bo’lmish Xo’ja Ahror Vali masjidining yonida an’anaviy sharq arxitekturasiga binoan bunyod etilgan. Madrasa Shahriston tepaligida joylashgan. Madrasa dastlab uch qavatli bo’lgan. Madrasaning chap qanoti masjid, o’ng qanoti esa darsxonalar sifatida ish yuritadi. \n\n Madrasaning faoliyati bilan ko‘pgina afsonalarni bog‘lashadi. Hududdagi yoshi katta qariyalarning so‘zlariga ko‘ra, ilgari madrasa hududida ommaviy qatllar o‘tkazilgan. Xiyonatkor ayollarni sharmanda qilish uchun hamda mahalliy aholiga ibrat bo‘lishi uchun eng baland minoradan uloqtirilardi ( Ammo ushbu faktlarni tasdiqlaydigan aniq arxeologik va yozma dalillar keltirilmagan*). Ko’kaldosh madrasasi XIX asrning 60-70-yillarida Toshkentning ‘rus istilosi’ davrida qattiq shikastlangan. 1886 yili rus muhandislari tomonidan xonaqolar va jome’ masjid qayta ta’mirlanish natijasida o’zining dastlabki me’moriy ko’rinishini tamoman yo’qotdi.  Oradan yillar o’tgach zilzilalar tufayli katta zarar ko’rgan. XX asrning boshida Toshkent shahri aholisi tomonidan ajratilgan hayriya bilan ta’mirlash ishlari olib borilgan, ammo oradan ko’p vaqt o’tmay ishlar to’xtab qolgan. \n\n 1996 yilgacha bajarilgan tiklash va ta’mirlash ishlari asosan, xalqning xayr-ehsonlari hisobiga bajarilgan. 1996 yildan boshlab ta’mirlash ishlari shahar hokimining Toshkent shahari ta’miri uchun ajratgan qurilish ashyolari hisobidan bergan yordami hamda O’zbekiston musulmonlari idorasi va madrasaga tushgan xayr-ehsonlar orqali amalga oshirilgan.Mustaqillik davridagi ta’mirlash ishlarida Buxorolik Ahror Asqarov va Madaniyat vazirligi yodgorliklarni saqlash instituti muhandisi, ‘Ko’kaldosh’ madrasasi qurilish loyihasi muallifi va ta’mirkor usta Mirobid Mirzoahmedov kabilar katta xizmat qildilar. \n\n Hozirgi kunda Ko’kaldosh madrasasida Islomiy ta’lim, arab va fors grammatikasi va turli xil boshqa diniy ta’limot beriladi. \n\n Madrasaning ichki devorlaridan birida qadimgi Rim maqoli – ‘Ars longa - vita brevia’ga o‘xshash yozuvni ko‘rishimiz mumkin: ‘O‘lim- muqarrar, ammo inson yaratgan mehnat abadiy qoladi’.",
        "img1": "https://raw.githubusercontent.com/Z9625/cards-data/refs/heads/main/Kukeldash2.jpg"
    }
    {
        "id": 3,
        "img": "https://raw.githubusercontent.com/Z9625/cards-data/refs/heads/main/Afrosiyob.jpg",
        "h1": "Afrasiyob",
        "p": "Afrosiyob eramizdan avvalgi 8—7-asrlarda hozirgi Samarqandning shimoli-sharqiy qismida tashkil etilgan. U 13-asrda moʻgʻullar istilosi paytida vayron boʻlgunga qadar Soʻgʻdiyonaning poytaxti boʻlgan.",
        "about": "Afrasiyob Samarqandning qadimiy markazi hisoblanadi. Afrasiyob xarobalari Samarqandning shimoli-sharqida, shahardan taxminan 10-15 metr balandlikda joylashgan. Shahar qadimiy manbalarda “Smarakanve” nomi bilan tilga olingan. Milodiy IV asrda Iskandar Zulqarnayn Samarqandni bosib olgandan keyin yunon manbalarida Marokanda nomi bilan qayd etilgan. Marokanda - Smarakanvening yunoncha tarjimasi. Somoniylar Movaronnahrda hokimiyat tepasiga kelgach, IX asrdan boshlab qadimgi Smaragand Samarqand deb atala boshlagan. \n\n11-15-asrlarda Samarqand turkiy adabiyotda Semizkent nomi bilan tilga olingan. 15-asrdan fors va turkiy manbalarda Samarqand nomi qoʻllanila boshlandi. \n\nShaharning ilk tarixi haqida yozma manbalarda juda kam ma’lumotlar mavjud. Biroq, eski shahardagi arxeologik qazishmalar ko'proq ma'lumot beradi. Afrosiybdan topilgan arxeologik materiallar Samarqandning eramizdan avvalgi 8—5-asrlarda Sugʻdning markaziy shahri sifatida mavjud boʻlganligini koʻrsatadi. Miloddan avvalgi 329 yilda shahar Iskandar Zulqarnayn qo'shinlari tomonidan vayron qilingan, uning izlari hali ham shahar istehkomlarida yaxshi saqlanib qolgan. Miloddan avvalgi 3—1-asrlarda Kushonlar sulolasi hukmronligi davrida shahar gullab-yashnash davrini boshidan kechirgan. Miloddan avvalgi 3-asrda shahar mudofaa qal'asi bilan o'ralgan. Bu qo‘rg‘on qoldiqlari Afrosiybning xarobalari joylashgan shimoliy qismida yaxshi saqlangan. Arxeologik materiallar va yozma manbalarga koʻra, bu davrda Samarqanddan Buyuk ipak yoʻli oʻtgan, ichki va tashqi savdo, hunarmandchilik rivojlangan. Ilk oʻrta asrlarda Samarqand Sugʻdning poytaxtiga aylanib, shaharning ijtimoiy-iqtisodiy hayotida tub oʻzgarishlar roʻy berib, nufuzli mavqega ega boʻldi. Badavlat-dexonlarning qudrati kuchaydi va shu bilan birga ularning saroylari joylashgan Afrosiaboning shimoliy qismi mudofaa devorlari bilan oʻralgan edi. Movarunnax va qo‘shni viloyatlarda ham xuddi shunday holat yuzaga keldi. Bu davrda Samarqand hukmdorlari “Ixshid”, Buxoro hukmdorlari esa “Buxorxudot” deb atalgan. 712 yilda Qutayba ibn Muslim boshchiligida arablar kelganida Samarqandning mudofaa devorlari mustahkam boʻlib, ularning atrofida ariq bor edi. Qutayba Fargʻona, Shosh va Samarqandga yordamga kelgan turk qoʻshinlarini magʻlub etdi, Sugʻd hukmdori Gurak esa tayanchsiz qolib, shaharning ichki qismini (shahristonni) arablarga topshirishga majbur boʻldi. Arxeologik topilmalar islom dini tasvirlangan haykallar va freskalar bolta bilan yo‘q qilinganligini isbotlaydi. \n\n1966-yil 13-iyulda respublika hukumati Afrosiaboni kompleks arxeologik oʻrganishni tashkil etish toʻgʻrisida maxsus qaror qabul qildi. \n\nAniq ilmiy usullarga asoslangan arxeologik tadqiqotlar shaharning nafaqat uzoq tarixini, balki uning turli davrlardagi tarixiy topografiyasini, shahar tuzilishini, rivojlanish bosqichlarini, shuningdek, bosqinlardan keyingi gullab-yashnash davrlarini ham ochib berish imkonini berdi. Samarqand hukmdorlari saroyi xalq uchun ochildi."
    },
    {
        "id": 2,
        "img": "https://raw.githubusercontent.com/Z9625/cards-data/refs/heads/main/Choponota.jpg",
        "h1": "Cho'ponota maqbarasi",
        "p": "Siz Samarqandda shahardan 100 metr balandlikda hech kim dafn etilmagan maqbarani ko'rganmisiz? Maqbaralar o'zi nega kerak?",
        "about": "Maqbaralarda asosan jamiyat arboblari, podsholar va sarkardalar daf etiladi. Ammo, Cho'ponota maqbarasi ulardan ajralib turadi. Cho'ponota maqbarasi dengiz sathidan 824 metr balandlikda va bu yerdan shaharning manzarasini tomosha qilish  mumkin. Arxeologik ishlar davomida bu yerdan askarlarning qurol aslahalari topilgan. Eng qizig'i shundaki, maqbaradan hech kimning qabri topilmagan. Bu maqbaraning atrofidagi gilidan go'ri amir maqbarasiga poydevor barpo etilgan. Keyinchalalik uning atrofida Ulugbek o'z rasadxonasini qurgan. Ba'zibir manbalarga ko'ra bu yer mayoq vazifasini ham o'tagan deyiladi."
    },
    {
        "id": 1,
        "img": "https://raw.githubusercontent.com/Z9625/cards-data/main/Ashm.jpg",
        "h1": "Ashratxona maqbarasi",
        "p": "Ashratxona maqbarasi Samarqand shahrining eski qismida, Registon yaqinida joylashgan bo‘lib, u 1464-yilda Temuriylar davrida, Amir Temurning nevarasi Mirzo Ulug‘bek davrida qurilgan.",
        "about": "Ashratxona maqbarasi Samarqand eski shaharining chekkasida joylashgan maqbara bo’lib Samarqanddagi me’moriy yodgorlik hisoblanadi. Shu kunlargacha maqbara nomi “Ishratxona” deb kelingan, ammo Samarqand davlat muzey-qo’riqxonasi ilmiy xodimlari maqabaraniung asl nomi “Ashratxona” (arabcha-forschada o’nta xona) ekanligini va nom talaffzudda o’zgarib ketganligini ta’kidlashadi.\n\n“Ashratxona” nomi ham shartli ravishda qo‘yilgan. Bu XVIII asrda Buxoro xonligida yuz bergan siyosiy inqiroz bilan bog‘liq. O‘shanda qabilalar o‘rtasidagi urushlar, bir necha marta yuz bergan bosqinlar natijasida hududda vabo tarqalib, aholi Samarqandni tark etadi. Buxoro amiri Shohmurod davrida qayta tiklangan Samarqand haqida turli hududlardan ko‘chirib keltirilgan aholi to‘liq bilimlarga ega bo‘lmasdan qadimiy me’moriy obidalarga o‘zlaricha nom beradilar.”\n\nXIX asrning 30-yillarida yozilgan “Samariya” asarida Ashratxona maqbarasi keltirilgan. Asarga asoslangan holda aytish mumkinki ushbu maqbara Habiba Sulton topshirig’i bilan qizi Sulton Hovandbeka uchun 1963 yilda to’la qonli barpo etilgan. Keyinchalik eda 23 nafar ayol va bolalar dafn etilgan sulolaviy qabrga aylandi.\n\nTemuriylarning taxtdan tushib, Shayboniylar kelgandan so’ng sulolaga oid maqbara va madrasalar qarovsiz qoladi. Shu holat Rossiya imperiyasi va Sovet ittifoqi davrida ham takrorlanib, e’tibordan chetda qoladi va asta sekinlik bilan xarobaga aylanib boradi. Misol uchun, 1897 yildagi yer silkinishi vaqtida maqbara kuchli zarar ko’radi. 1902 yilda esa gumbazi qulab tushadi."
    }
]
